taxonomy_generator/__init__.py
taxonomy_generator/configuration.py
taxonomy_generator/graph.py
taxonomy_generator/prompts.py
taxonomy_generator/state.py
taxonomy_generator/utils.py
taxonomy_generator/nodes/__init__.py
taxonomy_generator/nodes/doc_labeler.py
taxonomy_generator/nodes/minibatches_generator.py
taxonomy_generator/nodes/runs_retriever.py
taxonomy_generator/nodes/summary_generator.py
taxonomy_generator/nodes/taxonomy_generator.py
taxonomy_generator/nodes/taxonomy_reviewer.py
taxonomy_generator/nodes/taxonomy_updater.py
taxonomy_generator/routing/__init__.py
taxonomy_generator/routing/should_review.py
delve_taxonomy_generator-0.0.4.dist-info/LICENSE
delve_taxonomy_generator-0.0.4.dist-info/METADATA
delve_taxonomy_generator-0.0.4.dist-info/WHEEL
delve_taxonomy_generator-0.0.4.dist-info/top_level.txt
delve_taxonomy_generator-0.0.4.dist-info/RECORD
