Metadata-Version: 2.2
Name: delve-taxonomy-generator
Version: 0.0.4
Summary: A taxonomy generator for unstructured data.
Author-email: Andres Torres <torres.andres@gmail.com>
License: MIT
Requires-Python: >=3.9
License-File: LICENSE
Requires-Dist: langgraph>=0.2.6
Requires-Dist: langchain-openai>=0.1.22
Requires-Dist: langchain-anthropic>=0.1.23
Requires-Dist: langchain>=0.2.14
Requires-Dist: langchain-fireworks>=0.1.7
Requires-Dist: python-dotenv>=1.0.1
Requires-Dist: langchain-community>=0.2.17
Requires-Dist: tavily-python>=0.4.0
Provides-Extra: dev
Requires-Dist: mypy>=1.11.1; extra == "dev"
Requires-Dist: ruff>=0.6.1; extra == "dev"
